tabula/__init__.py
tabula/backend.py
tabula/file_util.py
tabula/io.py
tabula/py.typed
tabula/tabula-1.0.5-jar-with-dependencies.jar
tabula/template.py
tabula/util.py
tabula/errors/__init__.py
tabula_py-2.10.0.dist-info/LICENSE
tabula_py-2.10.0.dist-info/METADATA
tabula_py-2.10.0.dist-info/WHEEL
tabula_py-2.10.0.dist-info/top_level.txt
tabula_py-2.10.0.dist-info/RECORD
