Metadata-Version: 2.1
Name: tabula-py
Version: 2.10.0
Summary: Simple wrapper for tabula-java, read tables from PDF into DataFrame
Author-email: Aki Ariga <chezou@gmail.com>
Maintainer-email: Aki Ariga <chezou@gmail.com>
License: The MIT License (MIT)
Project-URL: Homepage, https://github.com/chezou/tabula-py
Project-URL: Bug Reports, https://github.com/chezou/tabula-py/issues
Project-URL: Funding, https://github.com/sponsors/chezou
Keywords: data frame,pdf,table
Classifier: Development Status :: 5 - Production/Stable
Classifier: Topic :: Text Processing :: General
Classifier: License :: OSI Approved :: MIT License
Classifier: Programming Language :: Python :: 3.13
Classifier: Programming Language :: Python :: 3.12
Classifier: Programming Language :: Python :: 3.11
Classifier: Programming Language :: Python :: 3.10
Classifier: Programming Language :: Python :: 3.9
Requires-Python: >=3.9
License-File: LICENSE
Requires-Dist: pandas>=0.25.3
Requires-Dist: numpy>1.24.4
Requires-Dist: distro
Provides-Extra: jpype
Requires-Dist: jpype1; extra == "jpype"
Provides-Extra: dev
Requires-Dist: pytest; extra == "dev"
Requires-Dist: ruff; extra == "dev"
Requires-Dist: mypy; extra == "dev"
Requires-Dist: Flake8-pyproject; extra == "dev"
Provides-Extra: test
Requires-Dist: pytest; extra == "test"
Provides-Extra: doc
Requires-Dist: sphinx==7.1.2; extra == "doc"
Requires-Dist: sphinx_rtd_theme==1.3.0; extra == "doc"
Requires-Dist: Jinja2==3.1.2; extra == "doc"
